qconf/__init__.py
qconf/qconfig.py
qconf/qparser.py
qconf/version.py
qconf-0.0.1.dist-info/METADATA
qconf-0.0.1.dist-info/WHEEL
qconf-0.0.1.dist-info/top_level.txt
qconf-0.0.1.dist-info/RECORD
