Metadata-Version: 2.1
Name: qconf
Version: 0.0.1
Summary: Quick Parser and Config
Home-page: https://github.com/vossenv/qconf
Maintainer: Danimae Vossen
Maintainer-email: vossen.dm@gmail.com
License: UNKNOWN
Platform: UNKNOWN
Classifier: Programming Language :: Python :: 3
Classifier: Intended Audience :: Developers
Requires-Dist: PyYAML
Requires-Dist: python-dateutil
Provides-Extra: test
Requires-Dist: pytest ; extra == 'test'
